README.md
setup.py
SimpleGraphics/__init__.py
SimpleGraphics/__main__.py
graphicssimple.egg-info/PKG-INFO
graphicssimple.egg-info/SOURCES.txt
graphicssimple.egg-info/dependency_links.txt
graphicssimple.egg-info/top_level.txt