Metadata-Version: 2.1
Name: graphicssimple
Version: 1.0.12
Summary: A simple graphics wrapper on top of tkinter
Home-page: https://cspages.ucalgary.ca/~bdstephe/217_P24/
Author: Ben Stephenson
Author-email: ben.stephenson@ucalgary.ca
Maintainer: Grygoriy Gromko
Maintainer-email: gr.gromko@gmail.com
Classifier: Programming Language :: Python :: 3
Classifier: License :: OSI Approved :: MIT License
Classifier: Operating System :: OS Independent
Requires-Python: >=3.1.0
